observablePy/Diffusible.py
observablePy/DiffusingModeEnum.py
observablePy/Observable.py
observablePy/ObservableProperty.py
observablePy/ObservableStore.py
observablePy/ObserverStore.py
observablePy/ObserverTypeEnum.py
observablePy/__init__.py
observablePy-0.2.2.dist-info/DESCRIPTION.rst
observablePy-0.2.2.dist-info/METADATA
observablePy-0.2.2.dist-info/RECORD
observablePy-0.2.2.dist-info/WHEEL
observablePy-0.2.2.dist-info/metadata.json
observablePy-0.2.2.dist-info/top_level.txt
