Metadata-Version: 2.0
Name: observablePy
Version: 0.2.2
Summary: Enable observable behavior.
Home-page: https://github.com/fredericklussier/ObservablePy
Author: Frederick Lussier
Author-email: frederick.lussier@hotmail.com
License: MIT
Download-URL: https://github.com/fredericklussier/ObservablePy/0.2.2
